railgun_mcp/__init__.py
railgun_mcp/__main__.py
railgun_mcp/models.py
railgun_mcp/server.py
railgun_mcp-0.2.1.dist-info/licenses/LICENSE
railgun_mcp-0.2.1.dist-info/METADATA
railgun_mcp-0.2.1.dist-info/WHEEL
railgun_mcp-0.2.1.dist-info/entry_points.txt
railgun_mcp-0.2.1.dist-info/top_level.txt
railgun_mcp-0.2.1.dist-info/RECORD
